{"data": {"image": "/data/upload/6/df1500d1-Convencional_Chao_Arv1_0m_square2.png"}, "annotations": [], "predictions": [{"model_version": "v1", "result": [{"id": "d10dae0a", "type": "polygonlabels", "value": {"points": [[94.3359375, 89.0625], [94.140625, 89.2578125], [94.140625, 89.84375], [94.3359375, 90.0390625], [94.53125, 90.0390625], [94.7265625, 89.84375], [94.921875, 89.84375], [94.921875, 89.0625]], "closed": true, "polygonlabels": ["single"]}, "origin": "manual", "to_name": "image", "from_name": "label", "image_rotation": 0, "original_width": 512, "original_height": 512}, {"id": "33b0150d", "type": "polygonlabels", "value": {"points": [[27.1484375, 75.390625], [26.953125, 75.5859375], [27.1484375, 75.78125], [27.734375, 75.78125], [27.9296875, 75.5859375], [27.734375, 75.390625]], "closed": true, "polygonlabels": ["overlapped"]}, "origin": "manual", "to_name": "image", "from_name": "label", "image_rotation": 0, "original_width": 512, "original_height": 512}, {"id": "3e069234", "type": "polygonlabels", "value": {"points": [[12.3046875, 36.5234375], [12.109375, 36.71875], [12.109375, 37.3046875], [12.3046875, 37.5], [12.890625, 37.5], [12.890625, 37.3046875], [13.0859375, 37.109375], [13.0859375, 36.9140625], [12.890625, 36.71875], [12.890625, 36.5234375]], "closed": true, "polygonlabels": ["single"]}, "origin": "manual", "to_name": "image", "from_name": "label", "image_rotation": 0, "original_width": 512, "original_height": 512}, {"id": "d4cb684b", "type": "polygonlabels", "value": {"points": [[0.0, 10.7421875], [0.0, 12.3046875], [5.2734375, 12.3046875], [5.46875, 12.5], [12.890625, 12.5], [13.0859375, 12.6953125], [15.234375, 12.6953125], [15.4296875, 12.890625], [28.125, 12.890625], [28.3203125, 13.0859375], [38.0859375, 13.0859375], [38.28125, 13.28125], [43.359375, 13.28125], [43.5546875, 13.4765625], [44.3359375, 13.4765625], [44.53125, 13.671875], [99.8046875, 13.671875], [99.8046875, 10.7421875]], "closed": true, "polygonlabels": ["overlapped"]}, "origin": "manual", "to_name": "image", "from_name": "label", "image_rotation": 0, "original_width": 512, "original_height": 512}], "score": 0.5, "mislabeling": 0, "project": 8}]}